vampytest/__init__.py
vampytest/__main__.py
vampytest/return_codes.py
vampytest/core/__init__.py
vampytest/core/run_state.py
vampytest/core/test_case.py
vampytest/core/assertions/__init__.py
vampytest/core/assertions/assertion_base.py
vampytest/core/assertions/assertion_conditional_base.py
vampytest/core/assertions/assertion_contains.py
vampytest/core/assertions/assertion_equals.py
vampytest/core/assertions/assertion_false.py
vampytest/core/assertions/assertion_identical.py
vampytest/core/assertions/assertion_instance.py
vampytest/core/assertions/assertion_not_contains.py
vampytest/core/assertions/assertion_not_equals.py
vampytest/core/assertions/assertion_not_identical.py
vampytest/core/assertions/assertion_raising.py
vampytest/core/assertions/assertion_states.py
vampytest/core/assertions/assertion_subtype.py
vampytest/core/assertions/assertion_true.py
vampytest/core/assertions/exception.py
vampytest/core/assertions/top_level.py
vampytest/core/contexts/__init__.py
vampytest/core/contexts/base.py
vampytest/core/contexts/calling.py
vampytest/core/contexts/garbage_collect.py
vampytest/core/contexts/output_capturing.py
vampytest/core/environment/__init__.py
vampytest/core/environment/configuration.py
vampytest/core/environment/constants.py
vampytest/core/environment/default.py
vampytest/core/environment/helpers.py
vampytest/core/environment/manager.py
vampytest/core/environment/scarletio_coroutine.py
vampytest/core/event_handling/__init__.py
vampytest/core/event_handling/base.py
vampytest/core/event_handling/default.py
vampytest/core/event_handling/default_output_writer.py
vampytest/core/event_handling/rendering_helpers/__init__.py
vampytest/core/event_handling/rendering_helpers/assertion_rendering.py
vampytest/core/event_handling/rendering_helpers/case_modifiers.py
vampytest/core/event_handling/rendering_helpers/load_failure_rendering.py
vampytest/core/event_handling/rendering_helpers/parameter_rendering.py
vampytest-0.0.25.dist-info/LICENSE
vampytest-0.0.25.dist-info/METADATA
vampytest-0.0.25.dist-info/WHEEL
vampytest-0.0.25.dist-info/entry_points.txt
vampytest-0.0.25.dist-info/top_level.txt
vampytest-0.0.25.dist-info/RECORD
